nonebot_plugin_furryyunhei/__init__.py
nonebot_plugin_furryyunhei/config.py
nonebot_plugin_furryyunhei-1.1.3.dist-info/licenses/LICENSE
nonebot_plugin_furryyunhei-1.1.3.dist-info/METADATA
nonebot_plugin_furryyunhei-1.1.3.dist-info/WHEEL
nonebot_plugin_furryyunhei-1.1.3.dist-info/top_level.txt
nonebot_plugin_furryyunhei-1.1.3.dist-info/RECORD
