Metadata-Version: 2.4
Name: nonebot-plugin-furryyunhei
Version: 1.1.3
Summary: NoneBot 插件用于查询 furry 云黑名单
Author-email: mofan <mofan@zhuiyenet.com>
License: MIT License
Project-URL: repository, https://github.com/mofan0423/nonebot-plugin-furryyunhei
Keywords: nonebot,furry,cloud-blacklist
Classifier: Development Status :: 4 - Beta
Classifier: Programming Language :: Python :: 3.10
Classifier: License :: OSI Approved :: MIT License
Classifier: Operating System :: OS Independent
Requires-Python: >=3.10
License-File: LICENSE
Requires-Dist: nonebot-adapter-onebot>=1.0.1
Requires-Dist: nonebot2>=2.4.1
Requires-Dist: httpx>=0.28.1
Dynamic: license-file
